kernelview/__init__.py
kernelview/cli.py
kernelview/core.py
kernelview-1.0.0.dist-info/METADATA
kernelview-1.0.0.dist-info/WHEEL
kernelview-1.0.0.dist-info/entry_points.txt
kernelview-1.0.0.dist-info/top_level.txt
kernelview-1.0.0.dist-info/RECORD
