Metadata-Version: 2.4
Name: kernelview
Version: 1.0.0
Summary: KernelView is a Python-based system information tool that provides detailed insights into your hardware and software, including CPU, memory, storage, OS, network, and installed programming languages.
Author-email: Soumyajit Das <codedbysoumyajit@proton.me>
License: MIT
Requires-Python: >=3.6
Requires-Dist: psutil>=5.0
Requires-Dist: setuptools>=59.6.0
